<FUNCTION address="0x10009b3b0L" name="+[CommonUtility getApplicationName]"><NODE addr="0x10009b418L">[ret_from_0x10009b3e8L_21661_64 valueForKey:]<NEXT addr="0x10009b448L" /></NODE><NODE addr="0x10009b3b0L">Start<NEXT addr="0x10009b3d0L" /></NODE><NODE addr="0x10009b3e8L">[ret_from_0x10009b3d0L_21660_64 infoDictionary]<NEXT addr="0x10009b418L" /></NODE><NODE addr="0x10009b448L">[ret_from_0x10009b3e8L_21661_64 valueForKey:]</NODE><NODE addr="0x10009b3d0L">[_OBJC_CLASS_$_NSBundle mainBundle]<NEXT addr="0x10009b3e8L" /></NODE></FUNCTION>