<FUNCTION address="0x1007a3058L" name="+[TDAAUtility getPurchaseDate]"><NODE addr="0x1007a3098L">[TDAAUtility getiTunesInfo]<NEXT addr="0x1007a30c4L" /></NODE><NODE addr="0x1007a310cL">[ret_from_0x1007a3100L_14823_64 init]<NEXT addr="0x1007a3128L" /></NODE><NODE addr="0x1007a3128L">[ret_from_0x1007a310cL_14824_64 setDateFormat:]<NEXT addr="0x1007a313cL" /></NODE><NODE addr="0x1007a3100L">[_OBJC_CLASS_$_NSDateFormatter alloc]<NEXT addr="0x1007a310cL" /></NODE><NODE addr="0x1007a30e0L">[ret_from_0x1007a30c4L_14821_64 objectForKey:]<NEXT addr="0x1007a3100L" /></NODE><NODE addr="0x1007a313cL">[ret_from_0x1007a310cL_14824_64 dateFromString:]<NEXT addr="0x1007a3154L" /></NODE><NODE addr="0x1007a3058L">Start<NEXT addr="0x1007a3098L" /></NODE><NODE addr="0x1007a318cL">[ret_from_0x1007a3174L_14829_64 longLongValue]</NODE><NODE addr="0x1007a30c4L">[ret_from_0x1007a3098L_14820_64 objectForKey:]<NEXT addr="0x1007a30e0L" /></NODE><NODE addr="0x1007a3154L">[ret_from_0x1007a313cL_14826_64 timeIntervalSince1970]<NEXT addr="0x1007a3174L" /></NODE><NODE addr="0x1007a3174L">[_OBJC_CLASS_$_NSNumber numberWithDouble:]<NEXT addr="0x1007a318cL" /></NODE></FUNCTION>