<FUNCTION address="0x1007a3728L" name="+[TDAAUtility getUpdateTime]"><NODE addr="0x1007a37ecL">[_OBJC_CLASS_$_NSFileManager defaultManager]<NEXT addr="0x1007a380cL" /></NODE><NODE addr="0x1007a386cL">[_OBJC_CLASS_$_NSNumber numberWithDouble:]<NEXT addr="0x1007a3884L" /></NODE><NODE addr="0x1007a3884L">[ret_from_0x1007a386cL_14748_64 longLongValue]</NODE><NODE addr="0x1007a37ccL">[ret_from_0x1007a37b4L_14741_64 path]<NEXT addr="0x1007a37ecL" /></NODE><NODE addr="0x1007a3834L">[ret_from_0x1007a380cL_14744_64 objectForKey:]<NEXT addr="0x1007a384cL" /></NODE><NODE addr="0x1007a380cL">[ret_from_0x1007a37ecL_14743_64 attributesOfItemAtPath:error:]<NEXT addr="0x1007a3834L" /></NODE><NODE addr="0x1007a376cL">[_OBJC_CLASS_$_NSBundle mainBundle]<NEXT addr="0x1007a3784L" /></NODE><NODE addr="0x1007a3728L">Start<NEXT addr="0x1007a376cL" /></NODE><NODE addr="0x1007a384cL">[ret_from_0x1007a3834L_14745_64 timeIntervalSince1970]<NEXT addr="0x1007a386cL" /></NODE><NODE addr="0x1007a37b4L">[ret_from_0x1007a3784L_14740_64 objectForKey:]<NEXT addr="0x1007a37ccL" /></NODE><NODE addr="0x1007a3784L">[ret_from_0x1007a376cL_14739_64 infoDictionary]<NEXT addr="0x1007a37b4L" /></NODE></FUNCTION>