<FUNCTION address="0x100793104L" name="+[TDAACrypto md5String:]"><NODE addr="0x1007931b0L">[_OBJC_CLASS_$_NSMutableString stringWithCapacity:]<NEXT addr="0x1007931ecL" /></NODE><NODE addr="0x100793184L">[ret_from__objc_retainAutorelease_1750_64 length]<NEXT addr="0x1007931b0L" /></NODE><NODE addr="0x100793104L">Start<NEXT addr="0x100793154L" /></NODE><NODE addr="0x100793154L">[reg_x2_1748_64 dataUsingEncoding:]<NEXT addr="0x100793170L" /></NODE><NODE addr="0x100793170L">[ret_from__objc_retainAutorelease_1750_64 bytes]<NEXT addr="0x100793184L" /></NODE><NODE addr="0x1007931ecL">[ret_from_0x1007931b0L_1754_64 appendFormat:]<NEXT addr="0x1007931ecL" /></NODE><NODE addr="0x1007931ecL">[ret_from_0x1007931b0L_1754_64 appendFormat:]</NODE></FUNCTION>