<FUNCTION address="0x10028b36cL" name="+[WXApi pay:]"><NODE addr="0x10028b4ecL">[ret_from_0x10028b3d8L_1388_64 wxApi_stringByEscapingForURLArgument]<NEXT addr="0x10028b51cL" /></NODE><NODE addr="0x10028b564L">[WeChatApiUtil getWeChatUrl:withAppSupportContentFlag:extraUrl:]<NEXT addr="0x10028b580L" /></NODE><NODE addr="0x10028b408L">[ret_from_0x10028b39cL_1385_64 length]<NEXT addr="0x10028b424L" /></NODE><NODE addr="0x10028b498L">[ret_from_0x10028b3ecL_1389_64 wxApi_stringByEscapingForURLArgument]<NEXT addr="0x10028b4a8L" /></NODE><NODE addr="0x10028b4b8L">[ret_from_0x10028b3b0L_1386_64 wxApi_stringByEscapingForURLArgument]<NEXT addr="0x10028b4c8L" /></NODE><NODE addr="0x10028b3c4L">[reg_x2_1384_64 prepayId]<NEXT addr="0x10028b3d8L" /></NODE><NODE addr="0x10028b424L">[ret_from_0x10028b3b0L_1386_64 length]<NEXT addr="0x10028b440L" /></NODE><NODE addr="0x10028b3b0L">[reg_x2_1384_64 partnerId]<NEXT addr="0x10028b3c4L" /></NODE><NODE addr="0x10028b590L">[ret_from_0x10028b580L_1403_64 openURL:]</NODE><NODE addr="0x10028b39cL">[reg_x2_1384_64 package]<NEXT addr="0x10028b3b0L" /></NODE><NODE addr="0x10028b4c8L">[ret_from_0x10028b3c4L_1387_64 wxApi_stringByEscapingForURLArgument]<NEXT addr="0x10028b4dcL" /></NODE><NODE addr="0x10028b580L">[_OBJC_CLASS_$_UIApplication sharedApplication]<NEXT addr="0x10028b590L" /></NODE><NODE addr="0x10028b4dcL">[reg_x2_1384_64 timeStamp]<NEXT addr="0x10028b4ecL" /></NODE><NODE addr="0x10028b478L">[ret_from_0x10028b3ecL_1389_64 length]<NEXT addr="0x10028b498L" /></NODE><NODE addr="0x10028b45cL">[ret_from_0x10028b3d8L_1388_64 length]<NEXT addr="0x10028b478L" /></NODE><NODE addr="0x10028b36cL">Start<NEXT addr="0x10028b39cL" /></NODE><NODE addr="0x10028b4a8L">[ret_from_0x10028b39cL_1385_64 wxApi_stringByEscapingForURLArgument]<NEXT addr="0x10028b4b8L" /></NODE><NODE addr="0x10028b51cL">[_OBJC_CLASS_$_NSString stringWithFormat:]<NEXT addr="0x10028b564L" /></NODE><NODE addr="0x10028b3d8L">[reg_x2_1384_64 sign]<NEXT addr="0x10028b3ecL" /></NODE><NODE addr="0x10028b3ecL">[reg_x2_1384_64 nonceStr]<NEXT addr="0x10028b408L" /></NODE><NODE addr="0x10028b440L">[ret_from_0x10028b3c4L_1387_64 length]<NEXT addr="0x10028b45cL" /></NODE></FUNCTION>