<FUNCTION address="0x10069a598L" name="-[AlipaySDK bossWithParams:scheme:callback:forceh5:]"><NODE addr="0x10069a770L">[ret_from_0x10069a75cL_452_64 initWithData:encoding:]<NEXT addr="0x10069a788L" /></NODE><NODE addr="0x10069a6b0L">[ret_from_0x10069a694L_448_64 transactionWillStart:]<NEXT addr="0x10069a70cL" /></NODE><NODE addr="0x10069a788L">[_OBJC_CLASS_$_NSString urlStrWithUnencode:]<NEXT addr="0x10069a854L" /><NEXT addr="0x10069a854L" /></NODE><NODE addr="0x10069a75cL">[_OBJC_CLASS_$_NSString alloc]<NEXT addr="0x10069a770L" /></NODE><NODE addr="0x10069a598L">Start<NEXT addr="0x10069a610L" /></NODE><NODE addr="0x10069a738L">[_OBJC_CLASS_$_NSJSONSerialization dataWithJSONObject:options:error:]<NEXT addr="0x10069a75cL" /></NODE><NODE addr="0x10069a8c4L">[ret_from_0x10069a854L_459_64 processOrder:callback:]</NODE><NODE addr="0x10069a624L">[AlipaySDK_instance_423_64 setCompletionBlock:]<NEXT addr="0x10069a694L" /></NODE><NODE addr="0x10069a70cL">[_OBJC_CLASS_$_NSDictionary dictionaryWithObjects:forKeys:count:]<NEXT addr="0x10069a738L" /></NODE><NODE addr="0x10069a854L">[AlipaySDK_instance_423_64 processor]<NEXT addr="0x10069a8c4L" /></NODE><NODE addr="0x10069a694L">[MQPTrackManager shared]<NEXT addr="0x10069a6b0L" /></NODE><NODE addr="0x10069a8c4L">[ret_from_0x10069a854L_455_64 processOrder:callback:]</NODE><NODE addr="0x10069a854L">[AlipaySDK_instance_423_64 processor]<NEXT addr="0x10069a8c4L" /></NODE><NODE addr="0x10069a610L">[AlipaySDK_instance_423_64 setSchemeStr:]<NEXT addr="0x10069a624L" /></NODE></FUNCTION>