<FUNCTION address="0x10048224cL" name="-[AMapSMCalloutMaskedBackgroundView layoutSubviews]"><NODE addr="0x10048255cL">[ret_from_0x100482524L_4999_64 setTransform:]</NODE><NODE addr="0x1004822ecL">[AMapSMCalloutMaskedBackgroundView_instance_4948_64 $width]<NEXT addr="0x1004822fcL" /></NODE><NODE addr="0x1004824f4L">[ret_from_0x1004824e0L_4989_64 $height]<NEXT addr="0x100482508L" /></NODE><NODE addr="0x10048247cL">[ret_from_0x100482454L_4988_64 set$y:]<NEXT addr="0x100482490L" /></NODE><NODE addr="0x100482490L">[AMapSMCalloutMaskedBackgroundView_instance_4948_64 arrowView]<NEXT addr="0x10048255cL" /></NODE><NODE addr="0x100482508L">[ret_from_0x100482454L_4988_64 set$y:]<NEXT addr="0x100482524L" /></NODE><NODE addr="0x1004823a0L">[ret_from_0x100482388L_4979_64 bounds]<NEXT addr="0x1004823bcL" /></NODE><NODE addr="0x1004824e0L">[AMapSMCalloutMaskedBackgroundView_instance_4948_64 containerView]<NEXT addr="0x1004824f4L" /></NODE><NODE addr="0x100482370L">[AMapSMCalloutMaskedBackgroundView_instance_4948_64 containerBorderView]<NEXT addr="0x100482388L" /></NODE><NODE addr="0x1004823bcL">[ret_from_0x100482370L_4978_64 setFrame:]<NEXT addr="0x1004823d8L" /></NODE><NODE addr="0x100482438L">[ret_from_0x1004823d8L_4983_64 set$x:]<NEXT addr="0x100482454L" /></NODE><NODE addr="0x1004822a0L">[AMapSMCalloutMaskedBackgroundView_instance_4948_64 $height]<NEXT addr="0x1004822ccL" /></NODE><NODE addr="0x1004823d8L">[AMapSMCalloutMaskedBackgroundView_instance_4948_64 arrowView]<NEXT addr="0x1004823f0L" /></NODE><NODE addr="0x1004822ccL">[AMapSMCalloutMaskedBackgroundView_instance_4948_64 containerView]<NEXT addr="0x1004822ecL" /></NODE><NODE addr="0x100482414L">[ret_from_0x100482400L_4985_64 $width]<NEXT addr="0x100482438L" /></NODE><NODE addr="0x1004823f0L">[AMapSMCalloutMaskedBackgroundView_instance_4948_64 arrowPoint]<NEXT addr="0x100482400L" /></NODE><NODE addr="0x100482388L">[AMapSMCalloutMaskedBackgroundView_instance_4948_64 containerView]<NEXT addr="0x1004823a0L" /></NODE><NODE addr="0x100482524L">[AMapSMCalloutMaskedBackgroundView_instance_4948_64 arrowView]<NEXT addr="0x10048255cL" /></NODE><NODE addr="0x10048255cL">[ret_from_0x100482490L_4992_64 setTransform:]</NODE><NODE addr="0x100482328L">[ret_from_0x100482314L_4974_64 $height]<NEXT addr="0x100482350L" /></NODE><NODE addr="0x10048224cL">Start<NEXT addr="0x100482288L" /></NODE><NODE addr="0x100482350L">[ret_from_0x1004822ccL_4971_64 setFrame:]<NEXT addr="0x100482370L" /></NODE><NODE addr="0x100482288L">[AMapSMCalloutMaskedBackgroundView_instance_4948_64 arrowPoint]<NEXT addr="0x1004822a0L" /></NODE><NODE addr="0x1004822fcL">[AMapSMCalloutMaskedBackgroundView_instance_4948_64 $height]<NEXT addr="0x100482314L" /></NODE><NODE addr="0x100482314L">[AMapSMCalloutMaskedBackgroundView_instance_4948_64 arrowView]<NEXT addr="0x100482328L" /></NODE><NODE addr="0x100482400L">[AMapSMCalloutMaskedBackgroundView_instance_4948_64 arrowView]<NEXT addr="0x100482414L" /></NODE><NODE addr="0x100482454L">[AMapSMCalloutMaskedBackgroundView_instance_4948_64 arrowView]<NEXT addr="0x1004824e0L" /><NEXT addr="0x10048247cL" /></NODE></FUNCTION>