<FUNCTION address="0x10049b834L" name="-[MAMapView getGestureAnchorPoint:]"><NODE addr="0x10049b88cL">[MAMapView_instance_4964_64 bounds]<NEXT addr="0x10049b8a0L" /></NODE><NODE addr="0x10049b960L">[reg_x2_4975_64 numberOfTouches]<NEXT addr="0x10049b97cL" /></NODE><NODE addr="0x10049b90cL">[reg_x2_4975_64 locationOfTouch:inView:]<NEXT addr="0x10049b928L" /></NODE><NODE addr="0x10049b97cL">[reg_x2_4975_64 locationInView:]<NEXT addr="0x10049b990L" /></NODE><NODE addr="0x10049b8a0L">[MAMapView_instance_4964_64 bounds]<NEXT addr="0x10049b8e8L" /></NODE><NODE addr="0x10049b9a0L">[MAMapView_instance_4964_64 bounds]</NODE><NODE addr="0x10049b990L">[MAMapView_instance_4964_64 bounds]<NEXT addr="0x10049b9a0L" /></NODE><NODE addr="0x10049b9a0L">[MAMapView_instance_4964_64 bounds]</NODE><NODE addr="0x10049b944L">[MAMapView_instance_4964_64 bounds]<NEXT addr="0x10049b9a0L" /></NODE><NODE addr="0x10049b928L">[reg_x2_4975_64 locationOfTouch:inView:]<NEXT addr="0x10049b944L" /></NODE><NODE addr="0x10049b8e8L">[reg_x2_4975_64 numberOfTouches]<NEXT addr="0x10049b960L" /><NEXT addr="0x10049b90cL" /></NODE><NODE addr="0x10049b834L">Start<NEXT addr="0x10049b88cL" /></NODE></FUNCTION>