<FUNCTION address="0x1004c484cL" name="-[MAAnnotationContainerView addAnnotationView:]"><NODE addr="0x1004c484cL">Start<NEXT addr="0x1004c4888L" /></NODE><NODE addr="0x1004c48fcL">[reg_x2_19470_64 setInternalDelegate:]<NEXT addr="0x1004c4914L" /></NODE><NODE addr="0x1004c48d4L">[reg_x2_19470_64 setSelected:]<NEXT addr="0x1004c48fcL" /></NODE><NODE addr="0x1004c4914L">[reg_x2_19470_64 annotation]<NEXT addr="0x1004c4938L" /></NODE><NODE addr="0x1004c4938L">[mem_20_19480_64 setObject:forKey:]</NODE><NODE addr="0x1004c4888L">[MAAnnotationContainerView_instance_19461_64 addSubview:]<NEXT addr="0x1004c489cL" /></NODE><NODE addr="0x1004c4938L">[mem_20_19476_64 setObject:forKey:]</NODE><NODE addr="0x1004c489cL">[reg_x2_19470_64 annotation]<NEXT addr="0x1004c48fcL" /><NEXT addr="0x1004c48d4L" /></NODE><NODE addr="0x1004c48fcL">[reg_x2_19470_64 setInternalDelegate:]<NEXT addr="0x1004c4914L" /></NODE><NODE addr="0x1004c4914L">[reg_x2_19470_64 annotation]<NEXT addr="0x1004c4938L" /></NODE></FUNCTION>