<FUNCTION address="0x1004f1c40L" name="-[MAOverlayRenderer clearTextures]"><NODE addr="0x1004f1cf8L">[ret_from_0x1004f1c88L_1151_64 deleteTextures:]</NODE><NODE addr="0x1004f1cd8L">[_OBJC_CLASS_$_NSArray arrayWithObjects:count:]<NEXT addr="0x1004f1cf8L" /></NODE><NODE addr="0x1004f1cacL">[_OBJC_CLASS_$_NSNumber numberWithInt:]<NEXT addr="0x1004f1cd8L" /></NODE><NODE addr="0x1004f1c40L">Start<NEXT addr="0x1004f1c88L" /></NODE><NODE addr="0x1004f1c88L">[MAOverlayRenderer_instance_1140_64 rendererDelegate]<NEXT addr="0x1004f1cacL" /></NODE></FUNCTION>