<FUNCTION address="0x100138904L" name="-[TGlllegaCompleteViewController viewDidLoad]"><NODE addr="0x100138970L">[ret_from_0x100138950L_2397_64 initWithFrame:style:]<NEXT addr="0x10013898cL" /></NODE><NODE addr="0x1001389ccL">[ret_from_0x1001389b8L_2406_64 bounds]<NEXT addr="0x1001389e4L" /></NODE><NODE addr="0x100138a60L">[TGlllegaCompleteViewController_instance_2385_64 setTableView:]<NEXT addr="0x100138a70L" /></NODE><NODE addr="0x100138c50L">[_OBJC_CLASS_$_NSMutableDictionary dictionary]<NEXT addr="0x100138c78L" /></NODE><NODE addr="0x100138d20L">[ret_from_0x100138cd8L_2436_64 setTipImage:]<NEXT addr="0x100138d3cL" /></NODE><NODE addr="0x100138a70L">[TGlllegaCompleteViewController_instance_2385_64 view]<NEXT addr="0x100138a8cL" /></NODE><NODE addr="0x100138ad0L">[TGlllegaCompleteViewController_instance_2385_64 tableView]<NEXT addr="0x100138af0L" /></NODE><NODE addr="0x100138abcL">[ret_from_0x100138970L_2403_64 setDataSource:]<NEXT addr="0x100138ad0L" /></NODE><NODE addr="0x1001389a8L">[ret_from_0x10013898cL_2404_64 bounds]<NEXT addr="0x1001389b8L" /></NODE><NODE addr="0x100138a8cL">[ret_from_0x100138a70L_2412_64 addSubview:]<NEXT addr="0x100138aa8L" /></NODE><NODE addr="0x100138bfcL">[TGlllegaCompleteViewController_instance_2385_64 setArrayKey:]<NEXT addr="0x100138c10L" /></NODE><NODE addr="0x100138be4L">[ret_from_0x100138970L_2403_64 setEstimatedSectionHeaderHeight:]<NEXT addr="0x100138bfcL" /></NODE><NODE addr="0x100138c3cL">[TGlllegaCompleteViewController_instance_2385_64 setRequestURL:]<NEXT addr="0x100138c50L" /></NODE><NODE addr="0x100138b78L">[ret_from_0x100138970L_2403_64 setSeparatorStyle:]<NEXT addr="0x100138b94L" /></NODE><NODE addr="0x100138ca8L">[TGlllegaCompleteViewController_instance_2385_64 tableView]<NEXT addr="0x100138cc4L" /></NODE><NODE addr="0x100138b94L">[_OBJC_CLASS_$_UIColor colorWithString:]<NEXT addr="0x100138bb4L" /></NODE><NODE addr="0x1001389fcL">[ret_from_0x1001389e4L_2408_64 statusBarFrame]<NEXT addr="0x100138a34L" /></NODE><NODE addr="0x100138d5cL">[ret_from_0x100138d3cL_2439_64 setTipTitle:]<NEXT addr="0x100138d78L" /></NODE><NODE addr="0x100138b5cL">[ret_from_0x100138970L_2403_64 registerNib:forCellReuseIdentifier:]<NEXT addr="0x100138b78L" /></NODE><NODE addr="0x100138cd8L">[TGlllegaCompleteViewController_instance_2385_64 tableView]<NEXT addr="0x100138d00L" /></NODE><NODE addr="0x100138c8cL">[TGlllegaCompleteViewController_instance_2385_64 setParams:]<NEXT addr="0x100138c9cL" /></NODE><NODE addr="0x10013898cL">[_OBJC_CLASS_$_UIScreen mainScreen]<NEXT addr="0x1001389a8L" /></NODE><NODE addr="0x100138af0L">[ret_from_0x100138ad0L_2416_64 setEstimatedRowHeight:]<NEXT addr="0x100138b14L" /></NODE><NODE addr="0x100138950L">[_OBJC_CLASS_$_UITableView alloc]<NEXT addr="0x100138970L" /></NODE><NODE addr="0x100138cc4L">[ret_from_0x100138ca8L_2434_64 setStartTip:]<NEXT addr="0x100138cd8L" /></NODE><NODE addr="0x100138c78L">[ret_from_0x100138c50L_2430_64 setObject:forKeyedSubscript:]<NEXT addr="0x100138c8cL" /></NODE><NODE addr="0x1001389e4L">[_OBJC_CLASS_$_UIApplication sharedApplication]<NEXT addr="0x1001389fcL" /></NODE><NODE addr="0x100138c9cL">[TGlllegaCompleteViewController_instance_2385_64 setupRefresh]<NEXT addr="0x100138ca8L" /></NODE><NODE addr="0x100138c10L">[TGIllegalModel class]<NEXT addr="0x100138c24L" /></NODE><NODE addr="0x100138bd0L">[ret_from_0x100138970L_2403_64 setEstimatedSectionFooterHeight:]<NEXT addr="0x100138be4L" /></NODE><NODE addr="0x100138d78L">[TGlllegaCompleteViewController_instance_2385_64 refreshOnePageShowHeader:]</NODE><NODE addr="0x100138a34L">[ret_from_0x100138970L_2403_64 setFrame:]<NEXT addr="0x100138a60L" /></NODE><NODE addr="0x1001389b8L">[_OBJC_CLASS_$_UIScreen mainScreen]<NEXT addr="0x1001389ccL" /></NODE><NODE addr="0x100138b14L">[ret_from_0x100138970L_2403_64 setRowHeight:]<NEXT addr="0x100138b34L" /></NODE><NODE addr="0x100138d3cL">[TGlllegaCompleteViewController_instance_2385_64 tableView]<NEXT addr="0x100138d5cL" /></NODE><NODE addr="0x100138bb4L">[ret_from_0x100138970L_2403_64 setBackgroundColor:]<NEXT addr="0x100138bd0L" /></NODE><NODE addr="0x100138c24L">[TGlllegaCompleteViewController_instance_2385_64 setModelClass:]<NEXT addr="0x100138c3cL" /></NODE><NODE addr="0x100138aa8L">[ret_from_0x100138970L_2403_64 setDelegate:]<NEXT addr="0x100138abcL" /></NODE><NODE addr="0x100138b34L">[_OBJC_CLASS_$_UINib nibWithNibName:bundle:]<NEXT addr="0x100138b5cL" /></NODE><NODE addr="0x100138d00L">[_OBJC_CLASS_$_UIImage imageNamed:]<NEXT addr="0x100138d20L" /></NODE><NODE addr="0x100138904L">Start<NEXT addr="0x100138950L" /></NODE></FUNCTION>