<FUNCTION address="0x1000be044L" name="-[TGOrderDetialController GetOrderDetailRequest]"><NODE addr="0x1000be0b0L">[ret_from_0x1000be06cL_2191_64 setObject:forKeyedSubscript:]<NEXT addr="0x1000be11cL" /></NODE><NODE addr="0x1000be044L">Start<NEXT addr="0x1000be06cL" /></NODE><NODE addr="0x1000be06cL">[_OBJC_CLASS_$_NSMutableDictionary dictionary]<NEXT addr="0x1000be088L" /></NODE><NODE addr="0x1000be11cL">[TGHttpManager TGPOSTAndLoading:parameters:name:success:failure:]</NODE><NODE addr="0x1000be088L">[TGOrderDetialController_instance_2184_64 orderId]<NEXT addr="0x1000be0b0L" /></NODE></FUNCTION>