<FUNCTION address="0x10001bf34L" name="-[ASNearMeViewController _turnOnGenius:]"><NODE addr="0x10001c10cL">[ret_from_0x10001bfd0L_911_64 addButtonWithTitle:]<NEXT addr="0x10001c120L" /></NODE><NODE addr="0x10001c120L">[ret_from_0x10001bfd0L_911_64 setCancelButtonIndex:]<NEXT addr="0x10001c140L" /></NODE><NODE addr="0x10001bfa4L">[ASNearMeViewController_instance_897_64 _showPlatformViewController]<NEXT addr="0x10001c0bcL" /></NODE><NODE addr="0x10001bfc4L">[_OBJC_CLASS_$_UIAlertView alloc]<NEXT addr="0x10001bfd0L" /></NODE><NODE addr="0x10001bfd0L">[ret_from_0x10001bfc4L_908_64 init]<NEXT addr="0x10001bfe4L" /></NODE><NODE addr="0x10001c0d4L">[ret_from_0x10001bfd0L_911_64 setTitle:]<NEXT addr="0x10001c0ecL" /></NODE><NODE addr="0x10001c150L">[ret_from_0x10001bfd0L_911_64 show]</NODE><NODE addr="0x10001c0bcL">[ASNearMeViewController_instance_897_64 startUpdatingLocation]</NODE><NODE addr="0x10001c030L">[ret_from_0x10001bfd0L_911_64 setTitle:]<NEXT addr="0x10001c04cL" /></NODE><NODE addr="0x10001bf34L">Start<NEXT addr="0x10001bf68L" /></NODE><NODE addr="0x10001c06cL">[ret_from_0x10001bfd0L_911_64 addButtonWithTitle:]<NEXT addr="0x10001c088L" /></NODE><NODE addr="0x10001bfe4L">[ASNearMeViewController_instance_897_64 clientContext]<NEXT addr="0x10001c0d4L" /><NEXT addr="0x10001c010L" /></NODE><NODE addr="0x10001c0bcL">[ASNearMeViewController_instance_897_64 _startLoadingTimer]</NODE><NODE addr="0x10001c120L">[ret_from_0x10001bfd0L_911_64 setCancelButtonIndex:]<NEXT addr="0x10001c140L" /></NODE><NODE addr="0x10001c0ecL">[ret_from_0x10001bfd0L_911_64 addButtonWithTitle:]<NEXT addr="0x10001c10cL" /></NODE><NODE addr="0x10001c010L">[ret_from_0x10001bfe4L_913_64 localizedStringForKey:]<NEXT addr="0x10001c030L" /></NODE><NODE addr="0x10001c140L">[ret_from_0x10001bfd0L_911_64 setDelegate:]<NEXT addr="0x10001c150L" /></NODE><NODE addr="0x10001c10cL">[ret_from_0x10001bfd0L_911_64 addButtonWithTitle:]<NEXT addr="0x10001c120L" /></NODE><NODE addr="0x10001c04cL">[ret_from_0x10001bfe4L_913_64 localizedStringForKey:]<NEXT addr="0x10001c06cL" /></NODE><NODE addr="0x10001bf94L">[ASNearMeViewController_instance_897_64 startUpdatingLocation]<NEXT addr="0x10001bfa4L" /></NODE><NODE addr="0x10001bf68L">[0 authorizationStatus]<NEXT addr="0x10001bfc4L" /><NEXT addr="0x10001c0bcL" /><NEXT addr="0x10001bf94L" /></NODE><NODE addr="0x10001c140L">[ret_from_0x10001bfd0L_911_64 setDelegate:]<NEXT addr="0x10001c150L" /></NODE><NODE addr="0x10001c088L">[ret_from_0x10001bfe4L_913_64 localizedStringForKey:]<NEXT addr="0x10001c10cL" /></NODE><NODE addr="0x10001c150L">[ret_from_0x10001bfd0L_911_64 show]</NODE></FUNCTION>